[
  {
    "id": "q_test1",
    "text": "Has Revolut partnered with any airport lounge in Tel Aviv again?",
    "enabled": true,
    "createdAt": "2026-07-11T17:43:21.197Z"
  },
  {
    "id": "q_mrnblfkexba27m",
    "text": "Has White Lotus Season 4 received an official release date?",
    "enabled": true,
    "createdAt": "2026-07-16T09:42:10.958Z"
  },
  {
    "id": "q_mrnbmh9ne6oerm",
    "text": "Is there a release date of the movie The Odyssey by Christopher Nolan?",
    "enabled": true,
    "createdAt": "2026-07-16T09:42:59.819Z"
  }
]
